[
  {
    "TransactionID": 0,
    "Actions": "Otar Tagviashvili deposited 500 GEL. Transaction date: 02-Mar-24 20:03:39"
  },
  {
    "TransactionID": 0,
    "Actions": "Otar Tagviashvili withdrawn 200 GEl. Transaction date: 02-Mar-24 20:04:21"
  },
  {
    "TransactionID": 1,
    "Actions": "Lela Datashvili deposited 500 GEL. Transaction date: 02-Mar-24 21:48:48"
  },
  {
    "TransactionID": 1,
    "Actions": "Lela Datashvili sent 200 GEl to Otar Tagviashvili. Transaction date: 02-Mar-24 21:49:05"
  },
  {
    "TransactionID": 0,
    "Actions": "Otar Tagviashvili received 200 GEl from Lela Datashvili. Transaction date: 02-Mar-24 21:49:05"
  }
]